aoc_tiles/__init__.py
aoc_tiles/animations.py
aoc_tiles/cli.py
aoc_tiles/colors.py
aoc_tiles/config.py
aoc_tiles/drawer.py
aoc_tiles/fonts.py
aoc_tiles/html.py
aoc_tiles/leaderboard.py
aoc_tiles/make_tiles.py
aoc_tiles/solutions.py
aoc_tiles/themes.py
aoc_tiles/resources/github_languages.yaml
aoc_tiles/resources/fonts/PaytoneOne.ttf
aoc_tiles/resources/fonts/SourceCodePro-Regular.otf
aoc_tiles-0.7.2.dist-info/METADATA
aoc_tiles-0.7.2.dist-info/WHEEL
aoc_tiles-0.7.2.dist-info/entry_points.txt
aoc_tiles-0.7.2.dist-info/licenses/LICENSE
aoc_tiles-0.7.2.dist-info/RECORD
