Metadata-Version: 2.4
Name: aoc-tiles
Version: 0.7.2
Summary: Fancy Advent of Code README tiles showing the completion status of the challenges per day
Author-email: "Brutenis Gliwa," <brutenis@gmail.com>
License-Expression: Apache-2.0
License-File: LICENSE
Requires-Python: >=3.8
Requires-Dist: gitpython<4,>=3.1.40
Requires-Dist: loguru<0.8,>=0.7.2
Requires-Dist: pillow<11,>=10.1.0
Requires-Dist: pyyaml<7,>=6.0.1
Requires-Dist: requests<3,>=2.31.0
Requires-Dist: rich<14,>=13.7.0
